systembridgedata/__init__.py
systembridgedata/_version.py
systembridgedata/module/__init__.py
systembridgedata/module/cpu.py
systembridgedata/module/disks.py
systembridgedata/module/media.py
systembridgedata/module/memory.py
systembridgedata/module/networks.py
systembridgedata/module/processes.py
systembridgedata/module/sensors.py
systembridgedata/module/system.py
systembridgedata-5.0.0.dev4.dist-info/LICENSE
systembridgedata-5.0.0.dev4.dist-info/METADATA
systembridgedata-5.0.0.dev4.dist-info/WHEEL
systembridgedata-5.0.0.dev4.dist-info/top_level.txt
systembridgedata-5.0.0.dev4.dist-info/RECORD
