Metadata-Version: 2.1
Name: systembridgedata
Version: 5.0.0.dev4
Summary: System Bridge Data
Home-page: https://github.com/timmo001/system-bridge-data
Author: Aidan Timson (Timmo)
Author-email: aidan@timmo.dev
License: Apache-2.0
Keywords: system-bridge
Requires-Python: >=3.11
License-File: LICENSE
Requires-Dist: incremental ==22.10.0
Requires-Dist: packaging >=24.0
Requires-Dist: plyer ==2.1.0
Requires-Dist: psutil ==5.9.8
Requires-Dist: systembridgeshared ==4.0.4
